{
    "AX": {
        "error": 0.007868097169694319,
        "error_type": "SEM",
        "filter_outliers_dict": {
            "filter_outliers": true,
            "iterations": 1,
            "std_devs": 2
        },
        "fit": "average",
        "value": -0.07166871670507322
    },
    "CDD": {
        "error": 8.799394607982575e-06,
        "error_type": "SEM",
        "filter_outliers_dict": {
            "filter_outliers": true,
            "iterations": 1,
            "std_devs": 10
        },
        "fit": "average",
        "value": 2.7140838683481067e-05
    },
    "H1": {
        "error": 0.0059977542739794425,
        "error_type": "SEM",
        "filter_outliers_dict": {
            "filter_outliers": true,
            "iterations": 1,
            "std_devs": 2
        },
        "fit": "average",
        "value": 0.028575217265680648
    },
    "H2": {
        "error": 0.0019788320096750353,
        "error_type": "SEM",
        "filter_outliers_dict": {
            "filter_outliers": true,
            "iterations": 1,
            "std_devs": 2
        },
        "fit": "average",
        "value": -0.06579561018946617
    },
    "L1": {
        "error": 0.00321820527302863,
        "error_type": "SEM",
        "filter_outliers_dict": {
            "filter_outliers": true,
            "iterations": 1,
            "std_devs": 2
        },
        "fit": "average",
        "value": 0.05232382963364052
    },
    "L2": {
        "error": 0.0063606600964032515,
        "error_type": "SEM",
        "filter_outliers_dict": {
            "filter_outliers": true,
            "iterations": 1,
            "std_devs": 2
        },
        "fit": "average",
        "value": -0.05624140813828913
    }
}