{
    "Ar36": {
        "error": 0.0019252286643250596,
        "error_type": "SEM",
        "filter_outliers_dict": {
            "filter_outliers": true,
            "iterations": 1,
            "std_devs": 2
        },
        "fit": "Parabolic",
        "value": 1.7720279359930056
    },
    "Ar37": {
        "error": 0.0037761868537980266,
        "error_type": "SEM",
        "filter_outliers_dict": {
            "filter_outliers": true,
            "iterations": 1,
            "std_devs": 2
        },
        "fit": "linear",
        "value": -0.03443115149936051
    },
    "Ar38": {
        "error": 0.0018679293945145176,
        "error_type": "SEM",
        "filter_outliers_dict": {
            "filter_outliers": true,
            "iterations": 1,
            "std_devs": 2
        },
        "fit": "linear",
        "value": 0.4031805919633485
    },
    "Ar39": {
        "error": 0.006804930179513168,
        "error_type": "SEM",
        "filter_outliers_dict": {
            "filter_outliers": true,
            "iterations": 1,
            "std_devs": 2
        },
        "fit": "Parabolic",
        "value": 0.0011779616758350198
    },
    "Ar40": {
        "error": 0.023465786242032986,
        "error_type": "SEM",
        "filter_outliers_dict": {
            "filter_outliers": true,
            "iterations": 1,
            "std_devs": 2
        },
        "fit": "Parabolic",
        "value": 522.8173554994596
    },
    "Ar41": {
        "error": 0.0016970096387179498,
        "error_type": "SEM",
        "filter_outliers_dict": {
            "filter_outliers": true,
            "iterations": 1,
            "std_devs": 2
        },
        "fit": "linear",
        "value": 0.02328754416288247
    }
}